ddr_general/__init__.py
ddr_general/utils.py
ddr_general/version.py
ddr_general-0.0.2.dist-info/METADATA
ddr_general-0.0.2.dist-info/WHEEL
ddr_general-0.0.2.dist-info/top_level.txt
ddr_general-0.0.2.dist-info/RECORD
