Metadata-Version: 2.1
Name: ddr-general
Version: 0.0.2
Summary: contains basic functionalities used frequently
Home-page: https://github.com/ddrathod121294/ddr_general
Author: Darshan Rathod
Author-email: darshan.rathod1994@gmail.com
Keywords: ddr,ddr_general
Classifier: Development Status :: 2 - Pre-Alpha
Classifier: Intended Audience :: Education
Classifier: Intended Audience :: Science/Research
Classifier: Natural Language :: English
Classifier: Topic :: Education
Classifier: Topic :: Scientific/Engineering
Classifier: Topic :: Scientific/Engineering :: Physics
Classifier: Programming Language :: Python :: 3.6
Requires-Python: >=3.6, <4
